{
	"configurations" : 
	[
		{
			"directories" : 
			[
				{
					"build" : ".",
					"jsonFile" : "directory-.-Debug-f5ebdc15457944623624.json",
					"minimumCMakeVersion" : 
					{
						"string" : "3.23"
					},
					"projectIndex" : 0,
					"source" : ".",
					"targetIndexes" : 
					[
						0
					]
				}
			],
			"name" : "Debug",
			"projects" : 
			[
				{
					"directoryIndexes" : 
					[
						0
					],
					"name" : "array",
					"targetIndexes" : 
					[
						0
					]
				}
			],
			"targets" : 
			[
				{
					"directoryIndex" : 0,
					"id" : "array::@6890427a1f51a3e7e1df",
					"jsonFile" : "target-array-Debug-5dee152b411e84282e38.json",
					"name" : "array",
					"projectIndex" : 0
				}
			]
		}
	],
	"kind" : "codemodel",
	"paths" : 
	{
		"build" : "/home/javohir/Desktop/projects/c++/abramyan/array/cmake-build-debug",
		"source" : "/home/javohir/Desktop/projects/c++/abramyan/array"
	},
	"version" : 
	{
		"major" : 2,
		"minor" : 4
	}
}
